pvcpie/kubernetesUtils.py
pvcpie/main.py
pvcpie-0.1.4.dist-info/METADATA
pvcpie-0.1.4.dist-info/WHEEL
pvcpie-0.1.4.dist-info/entry_points.txt
pvcpie-0.1.4.dist-info/RECORD
