Metadata-Version: 2.1
Name: pvcpie
Version: 0.1.4
Summary: Package to get PVC usage information in a cluster.
Author: Ujjwal
Author-email: ujjwalkadam22@gmail.com
Requires-Python: >=3.9,<4.0
Classifier: Programming Language :: Python :: 3
Classifier: Programming Language :: Python :: 3.9
Classifier: Programming Language :: Python :: 3.10
Classifier: Programming Language :: Python :: 3.11
Classifier: Programming Language :: Python :: 3.12
Requires-Dist: kubernetes (>=30.1.0,<31.0.0)
Requires-Dist: pandas (>=2.2.2,<3.0.0)
Requires-Dist: prettytable (>=3.10.0,<4.0.0)
Requires-Dist: requests (>=2.32.3,<3.0.0)
